metapensiero/sphinx/patchdb/__init__.py
metapensiero/sphinx/patchdb/contexts/__init__.py
metapensiero/sphinx/patchdb/contexts/firebird.py
metapensiero/sphinx/patchdb/contexts/mysql.py
metapensiero/sphinx/patchdb/contexts/postgres.py
metapensiero/sphinx/patchdb/contexts/python.py
metapensiero/sphinx/patchdb/contexts/sql.py
metapensiero/sphinx/patchdb/contexts/sqlite.py
metapensiero/sphinx/patchdb/locale/__init__.py
metapensiero/sphinx/patchdb/manager.py
metapensiero/sphinx/patchdb/patch.py
metapensiero/sphinx/patchdb/planner.py
metapensiero/sphinx/patchdb/pup.py
metapensiero/sphinx/patchdb/script.py
metapensiero/sphinx/patchdb/states.py
metapensiero_sphinx_patchdb-4.4.dist-info/METADATA
metapensiero_sphinx_patchdb-4.4.dist-info/WHEEL
metapensiero_sphinx_patchdb-4.4.dist-info/entry_points.txt
metapensiero_sphinx_patchdb-4.4.dist-info/RECORD
