Metadata-Version: 2.1
Name: metapensiero.sphinx.patchdb
Version: 4.4
Summary: Extract scripts from a reST document and apply them in order.
Author-Email: Lele Gaifax <lele@metapensiero.it>
License: GPL-3.0-or-later
Classifier: Programming Language :: Python
Classifier: Programming Language :: Python :: 3
Classifier: Programming Language :: Python :: 3.13
Classifier: Programming Language :: Python :: 3.14
Classifier: Development Status :: 5 - Production/Stable
Classifier: Intended Audience :: Developers
Classifier: License :: OSI Approved :: GNU General Public License v3 or later (GPLv3+)
Classifier: Topic :: Database
Classifier: Topic :: Utilities
Classifier: Framework :: Sphinx :: Extension
Classifier: Environment :: Console
Classifier: Natural Language :: English
Classifier: Natural Language :: Italian
Project-URL: Changelog, https://gitlab.com/metapensiero/metapensiero.sphinx.patchdb/-/blob/master/CHANGES.rst
Project-URL: Source, https://gitlab.com/metapensiero/metapensiero.sphinx.patchdb
Requires-Python: >=3.10
Requires-Dist: enlighten
Requires-Dist: sqlparse>=0.5.0
Provides-Extra: dev
Requires-Dist: babel; extra == "dev"
Requires-Dist: build; extra == "dev"
Requires-Dist: bump-to-version; extra == "dev"
Requires-Dist: pygments; extra == "dev"
Requires-Dist: sphinx; extra == "dev"
Requires-Dist: twine; extra == "dev"
